{
    "display": {
      "icon": {
        "id": "minecraft:netherite_axe"
      },
      "title": "Sharknado!!!!!",
      "description": "Get 15 kills in one round",
      "frame": "challenge",
      "show_toast": true,
      "announce_to_chat": true,
      "hidden": true
    },
    "parent": "game:general/rare/kill_10_in_one_round",
    "criteria": {
      "requirement": {
        "trigger": "minecraft:impossible"
      }
    },
    "rewards": {
      "function": "game:levels/epic_advancement"
    }
  }
  